<annotation>
	<folder>train</folder>
	<filename>40592676.jpg</filename>
	<path>C:\tensorflow1\models\research\object_detection\images\train\40592676.jpg</path>
	<source>
		<database>Unknown</database>
	</source>
	<size>
		<width>867</width>
		<height>1300</height>
		<depth>3</depth>
	</size>
	<segmented>0</segmented>
	<object>
		<name>casco</name>
		<pose>Unspecified</pose>
		<truncated>0</truncated>
		<difficult>0</difficult>
		<bndbox>
			<xmin>369</xmin>
			<ymin>123</ymin>
			<xmax>588</xmax>
			<ymax>294</ymax>
		</bndbox>
	</object>
</annotation>
